listoapi/__init__.py
listoapi/api.py
listoapi/banks.py
listoapi/cash_advances.py
listoapi/cfdi_payments.py
listoapi/documents.py
listoapi/exchange_rate.py
listoapi/expenses.py
listoapi/filings.py
listoapi/invoices.py
listoapi/invoicing.py
listoapi/items.py
listoapi/openssl.exe
listoapi/payments.py
listoapi/purchases.py
listoapi/reports.py
listoapi/setup.py
listoapi/suppliers.py
listoapi-0.1.78.dist-info/METADATA
listoapi-0.1.78.dist-info/WHEEL
listoapi-0.1.78.dist-info/top_level.txt
listoapi-0.1.78.dist-info/RECORD
